yahoo_finance_async/__init__.py
yahoo_finance_async/api.py
yahoo_finance_async-0.1.4.dist-info/licenses/LICENSE
yahoo_finance_async-0.1.4.dist-info/WHEEL
yahoo_finance_async-0.1.4.dist-info/METADATA
yahoo_finance_async-0.1.4.dist-info/RECORD
