Metadata-Version: 2.4
Name: yahoo_finance_async
Version: 0.1.4
Summary: A Python async API wrapper for the deprecated (but currently still working) Yahoo Finance API
Home-page: https://github.com/ttamg/yahoo-finance-async
Keywords: yahoo, finance, python, API, async
Author: Matt Gosden
Author-email: mdgosden@gmail.com
Requires-Python: >=3.6
License: MIT
Classifier: License :: OSI Approved :: MIT License
Classifier: Intended Audience :: Developers
Classifier: Intended Audience :: Financial and Insurance Industry
Classifier: Programming Language :: Python :: 3 :: Only
Classifier: Topic :: Office/Business :: Financial :: Investment
License-File: LICENSE
Requires-Dist: aiohttp>=3.6.2
Requires-Dist: aiodns>=2.0.0
